x_client_transaction/__init__.py
x_client_transaction/constants.py
x_client_transaction/cubic_curve.py
x_client_transaction/interpolate.py
x_client_transaction/rotation.py
x_client_transaction/transaction.py
x_client_transaction/utils.py
xclienttransaction-1.0.1.dist-info/LICENSE
xclienttransaction-1.0.1.dist-info/METADATA
xclienttransaction-1.0.1.dist-info/WHEEL
xclienttransaction-1.0.1.dist-info/top_level.txt
xclienttransaction-1.0.1.dist-info/RECORD
